bluesky_blissdata/__init__.py
bluesky_blissdata/dispatcher.py
bluesky_blissdata/run.py
bluesky_blissdata-0.0.1.dist-info/LICENSE.txt
bluesky_blissdata-0.0.1.dist-info/METADATA
bluesky_blissdata-0.0.1.dist-info/WHEEL
bluesky_blissdata-0.0.1.dist-info/entry_points.txt
bluesky_blissdata-0.0.1.dist-info/top_level.txt
bluesky_blissdata-0.0.1.dist-info/RECORD
