Metadata-Version: 2.1
Name: bluesky-blissdata
Version: 0.0.1
Summary: Plugin for BlissData for bluesky document streaming.
Home-page: https://gitlab.desy.de/fs-ec/bluesky_blissdata
Author: Udai Singh
Author-email: udai.singh@desy.de
License: MIT
Project-URL: Documentation, https://pyscaffold.org/
Platform: any
Classifier: Development Status :: 4 - Beta
Classifier: Programming Language :: Python
License-File: LICENSE.txt
Requires-Dist: bluesky-queueserver
Requires-Dist: blissdata
Requires-Dist: importlib-metadata; python_version < "3.8"
Provides-Extra: testing
Requires-Dist: setuptools; extra == "testing"
Requires-Dist: pytest; extra == "testing"
Requires-Dist: pytest-cov; extra == "testing"
